tests/__init__.py
tests/xfeat/__init__.py
tests/xfeat/test_helper.py
tests/xfeat/test_optuna_selector.py
tests/xfeat/test_pipeline.py
tests/xfeat/test_utils.py
tests/xfeat/cat_encoder/__init__.py
tests/xfeat/cat_encoder/test_concat_combination.py
tests/xfeat/cat_encoder/test_count_encoder.py
tests/xfeat/cat_encoder/test_label_encoder.py
tests/xfeat/cat_encoder/test_target_encoder.py
tests/xfeat/cat_encoder/test_user_defined_label_encoder.py
tests/xfeat/generic_encoder/__init__.py
tests/xfeat/generic_encoder/test_lambda_encoder.py
tests/xfeat/optuna_selector/__init__.py
tests/xfeat/optuna_selector/test_group_combination_explorer.py
tests/xfeat/selector/__init__.py
tests/xfeat/selector/test_elimination.py
tests/xfeat/selector/test_filter.py
tests/xfeat/selector/test_gbdt_selector.py
xfeat/__init__.py
xfeat/helper.py
xfeat/types.py
xfeat/utils.py
xfeat/base/__init__.py
xfeat/base/_mixin.py
xfeat/cat_encoder/__init__.py
xfeat/cat_encoder/_basic_encoder.py
xfeat/cat_encoder/_concat_combination.py
xfeat/cat_encoder/_count_encoder.py
xfeat/cat_encoder/_target_encoder.py
xfeat/cat_encoder/_user_defined_labelencoder.py
xfeat/generic_encoder/__init__.py
xfeat/generic_encoder/_lambda_encoder.py
xfeat/num_encoder/__init__.py
xfeat/num_encoder/_arithmetic_combinations.py
xfeat/num_encoder/_select_numerical.py
xfeat/optuna_selector/__init__.py
xfeat/optuna_selector/_gbdt_feature_explorer.py
xfeat/optuna_selector/_group_combination_explorer.py
xfeat/optuna_selector/_kbest_explorer.py
xfeat/pipeline/__init__.py
xfeat/pipeline/_pipeline.py
xfeat/selector/__init__.py
xfeat/selector/_elimination.py
xfeat/selector/_filter.py
xfeat/selector/_gbdt_selector.py
xfeat-0.1.1.dist-info/LICENSE
xfeat-0.1.1.dist-info/METADATA
xfeat-0.1.1.dist-info/WHEEL
xfeat-0.1.1.dist-info/entry_points.txt
xfeat-0.1.1.dist-info/top_level.txt
xfeat-0.1.1.dist-info/RECORD
